odoo10_addon_maintenance_plan-10.0.1.0.0-py2.7-nspkg.pth
odoo/addons/maintenance_plan/README.rst
odoo/addons/maintenance_plan/__init__.py
odoo/addons/maintenance_plan/__manifest__.py
odoo/addons/maintenance_plan/hooks.py
odoo/addons/maintenance_plan/data/demo_maintenance_plan.xml
odoo/addons/maintenance_plan/models/__init__.py
odoo/addons/maintenance_plan/models/maintenance.py
odoo/addons/maintenance_plan/security/ir.model.access.csv
odoo/addons/maintenance_plan/tests/__init__.py
odoo/addons/maintenance_plan/tests/test_maintenance_plan.py
odoo/addons/maintenance_plan/views/maintenance.xml
odoo10_addon_maintenance_plan-10.0.1.0.0.dist-info/DESCRIPTION.rst
odoo10_addon_maintenance_plan-10.0.1.0.0.dist-info/METADATA
odoo10_addon_maintenance_plan-10.0.1.0.0.dist-info/RECORD
odoo10_addon_maintenance_plan-10.0.1.0.0.dist-info/WHEEL
odoo10_addon_maintenance_plan-10.0.1.0.0.dist-info/metadata.json
odoo10_addon_maintenance_plan-10.0.1.0.0.dist-info/namespace_packages.txt
odoo10_addon_maintenance_plan-10.0.1.0.0.dist-info/top_level.txt
