Metadata-Version: 2.0
Name: odoo10-addon-maintenance-plan
Version: 10.0.1.0.0
Summary: Extends preventive maintenance planning
Home-page: http://www.camptocamp.com
Author: Odoo Community Association (OCA), Camptocamp SA
Author-email: support@odoo-community.org
License: AGPL-3
Platform: UNKNOWN
Classifier: Programming Language :: Python :: 2.7
Classifier: Framework :: Odoo
Classifier: License :: OSI Approved :: GNU Affero General Public License v3
Requires-Dist: odoo (<10.1dev,>=10.0)
